setuptools_openapi_generator/__init__.py
setuptools_openapi_generator/_version.py
setuptools_openapi_generator/config.py
setuptools_openapi_generator/generator.py
setuptools_openapi_generator/integration.py
setuptools_openapi_generator-0.1.1.dist-info/LICENSE
setuptools_openapi_generator-0.1.1.dist-info/METADATA
setuptools_openapi_generator-0.1.1.dist-info/WHEEL
setuptools_openapi_generator-0.1.1.dist-info/entry_points.txt
setuptools_openapi_generator-0.1.1.dist-info/top_level.txt
setuptools_openapi_generator-0.1.1.dist-info/RECORD
